settings_helper/__init__.py
settings_helper/settings.ini
tests/__init__.py
tests/test_settings.py
settings_helper-0.0.18.dist-info/LICENSE.txt
settings_helper-0.0.18.dist-info/METADATA
settings_helper-0.0.18.dist-info/WHEEL
settings_helper-0.0.18.dist-info/top_level.txt
settings_helper-0.0.18.dist-info/RECORD
