Metadata-Version: 2.1
Name: settings-helper
Version: 0.0.18
Summary: Helpers to get specific settings from a particular section of a settings.ini file
Home-page: https://github.com/kenjyco/settings-helper
Author: Ken
Author-email: kenjyco@gmail.com
License: MIT
Download-URL: https://github.com/kenjyco/settings-helper/tarball/v0.0.18
Keywords: settings,config,environment variables,ini,ini file,ini parser,helper,kenjyco
Platform: UNKNOWN
Classifier: Development Status :: 4 - Beta
Classifier: Environment :: Console
Classifier: Intended Audience :: Developers
Classifier: License :: OSI Approved :: MIT License
Classifier: Operating System :: MacOS :: MacOS X
Classifier: Operating System :: POSIX :: Linux
Classifier: Programming Language :: Python :: 3.5
Classifier: Programming Language :: Python :: 3.6
Classifier: Programming Language :: Python :: 3.7
Classifier: Programming Language :: Python :: 3.8
Classifier: Programming Language :: Python :: 3.9
Classifier: Programming Language :: Python :: 3.10
Classifier: Programming Language :: Python :: 3.11
Classifier: Programming Language :: Python :: 3.12
Classifier: Programming Language :: Python :: 3.13
Classifier: Programming Language :: Python
Classifier: Topic :: Software Development :: Libraries
Classifier: Topic :: Utilities
Requires-Dist: bg-helper
Requires-Dist: input-helper
